[{"name":"Снифф","hunger":0,"location":"TopFloor","family":"CloseFriends","inventory":{"inventory":[]}},{"name":"Муми-тролль","hunger":0,"location":"TopFloor","family":"MoominFamily","inventory":{"inventory":[]}},{"name":"Снусмумрик","hunger":0,"location":"TopFloor","family":"CloseFriends","inventory":{"inventory":[]}},{"name":"Хемуль","hunger":0,"location":"Hill","family":"CloseFriends","inventory":{"inventory":[]}},{"name":"Фрейкен Снорк","hunger":0,"location":"TopFloor","family":"CloseFriends","inventory":{"inventory":[]}}]